azeemai-0.0.0.dist-info/licenses/LICENSE
versein/__init__.py
azeemai-0.0.0.dist-info/METADATA
azeemai-0.0.0.dist-info/WHEEL
azeemai-0.0.0.dist-info/top_level.txt
azeemai-0.0.0.dist-info/RECORD
