Metadata-Version: 2.4
Name: azeemai
Version: 0.0.0
Summary: A voice AI SDK for assistants
Author-email: Noureddin Abusharekh <nour@versein.com>, Muhammad Azeem <azeem@versein.com>
License: MIT License
Project-URL: Homepage, https://versein.com
Project-URL: GitHub, https://github.com/versein/versein
Project-URL: Documentation, https://versein.com/docs
Project-URL: Changelog, https://github.com/versein/versein/releases
Project-URL: Issues, https://github.com/versein/versein/issues
Classifier: Development Status :: 3 - Alpha
Classifier: License :: OSI Approved :: Apache Software License
Classifier: Programming Language :: Python :: 3.11
Classifier: Programming Language :: Python :: 3.12
Classifier: Programming Language :: Python :: 3.13
Requires-Python: >=3.10
License-File: LICENSE
Provides-Extra: dev
Provides-Extra: console
Dynamic: license-file
